facify/__init__.py
facify/detect.py
facify/show.py
facify/data/haarcascade_frontalface_default.xml
facify-0.1.dist-info/METADATA
facify-0.1.dist-info/WHEEL
facify-0.1.dist-info/top_level.txt
facify-0.1.dist-info/RECORD
