Metadata-Version: 2.1
Name: facify
Version: 0.1
Summary: A simple and efficient tool for extracting faces from images using face detection Haar cascade.
Author: Digvijay Patil
Author-email: patildigvijay7878@gmail.com
Requires-Dist: opencv-python
